bluepyparallel/__init__.py
bluepyparallel/database.py
bluepyparallel/evaluator.py
bluepyparallel/parallel.py
bluepyparallel/utils.py
BluePyParallel-0.2.2.dist-info/AUTHORS.md
BluePyParallel-0.2.2.dist-info/LICENSE.txt
BluePyParallel-0.2.2.dist-info/METADATA
BluePyParallel-0.2.2.dist-info/WHEEL
BluePyParallel-0.2.2.dist-info/top_level.txt
BluePyParallel-0.2.2.dist-info/RECORD
