Metadata-Version: 2.1
Name: BluePyParallel
Version: 0.2.2
Summary: Provides an embarrassingly parallel tool with sql backend.
Author: Blue Brain Project, EPFL
License: Apache License 2.0
Project-URL: Homepage, https://BluePyParallel.readthedocs.io
Project-URL: Repository, https://github.com/BlueBrain/BluePyParallel
Project-URL: Tracker, https://github.com/BlueBrain/BluePyParallel/issues
Classifier: Development Status :: 4 - Beta
Classifier: Intended Audience :: Developers
Classifier: Programming Language :: Python
Classifier: Programming Language :: Python :: 3
Classifier: Programming Language :: Python :: 3.8
Classifier: Programming Language :: Python :: 3.9
Classifier: Programming Language :: Python :: 3.10
Classifier: Programming Language :: Python :: 3.11
Classifier: Programming Language :: Python :: 3.12
Classifier: Topic :: Scientific/Engineering :: Bio-Informatics
Requires-Python: >=3.8
License-File: LICENSE.txt
License-File: AUTHORS.md
Requires-Dist: pandas >=1.3
Requires-Dist: ipyparallel >=6.3
Requires-Dist: dask[dataframe,distributed] >=2021.11
Requires-Dist: dask-mpi >=2021.11
Requires-Dist: distributed >=2021.11
Requires-Dist: packaging >=20
Requires-Dist: sqlalchemy >=1.4.24
Requires-Dist: sqlalchemy-utils >=0.37.2
Requires-Dist: tqdm >=3.7
Requires-Dist: sqlalchemy <2 ; python_version < "3.8"
Provides-Extra: docs
Requires-Dist: m2r2 ; extra == 'docs'
Requires-Dist: sphinx ; extra == 'docs'
Requires-Dist: sphinx-bluebrain-theme ; extra == 'docs'
Provides-Extra: test
Requires-Dist: mpi4py >=3.0.1 ; extra == 'test'
Requires-Dist: packaging >=20 ; extra == 'test'
Requires-Dist: pytest >=6.1 ; extra == 'test'
Requires-Dist: pytest-benchmark >=3.4 ; extra == 'test'
Requires-Dist: pytest-cov >=3 ; extra == 'test'
Requires-Dist: pytest-html >=3.1 ; extra == 'test'
